audioclass/__init__.py
audioclass/constants.py
audioclass/postprocess.py
audioclass/preprocess.py
audioclass/utils.py
audioclass/batch/__init__.py
audioclass/batch/base.py
audioclass/batch/process.py
audioclass/batch/simple.py
audioclass/batch/tensorflow.py
audioclass/data/BirdNET_GLOBAL_6K_V2.4/saved_model.pb
audioclass/data/BirdNET_GLOBAL_6K_V2.4/variables/variables.data-00000-of-00001
audioclass/data/BirdNET_GLOBAL_6K_V2.4/variables/variables.index
audioclass/data/perch/label.csv
audioclass/models/__init__.py
audioclass/models/base.py
audioclass/models/birdnet.py
audioclass/models/birdnet_analyzer.py
audioclass/models/perch.py
audioclass/models/tensorflow.py
audioclass/models/tflite.py
audioclass-0.2.5.dist-info/METADATA
audioclass-0.2.5.dist-info/WHEEL
audioclass-0.2.5.dist-info/licenses/LICENCE
audioclass-0.2.5.dist-info/RECORD
