Metadata-Version: 2.4
Name: audioclass
Version: 0.2.5
Summary: A Python package providing a common interface for running machine learning models for audio classification tasks.
Author-email: Santiago Martinez Balvanera <santiago.mbal@gmail.com>
License: MIT
License-File: LICENCE
Requires-Python: <3.12,>=3.9
Requires-Dist: netcdf4>=1.6.5
Requires-Dist: pandas>=2.0
Requires-Dist: pyarrow>=14.0
Requires-Dist: requests>=2.0
Requires-Dist: soundevent[audio]>=2.2
Requires-Dist: tqdm>=4.66.4
Provides-Extra: all
Requires-Dist: tensorflow-hub>=0.16.1; extra == 'all'
Requires-Dist: tensorflow>=2.0; extra == 'all'
Provides-Extra: birdnet
Requires-Dist: numpy<2; extra == 'birdnet'
Requires-Dist: tflite-runtime>=2.14.0; extra == 'birdnet'
Provides-Extra: birdnet-analyzer
Requires-Dist: tensorflow-hub>=0.16.1; extra == 'birdnet-analyzer'
Requires-Dist: tensorflow>=2.0; extra == 'birdnet-analyzer'
Provides-Extra: perch
Requires-Dist: tensorflow-hub>=0.16.1; extra == 'perch'
Requires-Dist: tensorflow>=2.0; extra == 'perch'
Provides-Extra: tensorflow
Requires-Dist: tensorflow-hub>=0.16.1; extra == 'tensorflow'
Requires-Dist: tensorflow>=2.0; extra == 'tensorflow'
Provides-Extra: tflite
Requires-Dist: numpy<2; extra == 'tflite'
Requires-Dist: tflite-runtime>=2.14.0; extra == 'tflite'
